next_meetup/__init__.py
next_meetup/next_meetup.py
next_meetup/tests/__init__.py
pelican_next_meetup-0.1.1.dist-info/top_level.txt
pelican_next_meetup-0.1.1.dist-info/METADATA
pelican_next_meetup-0.1.1.dist-info/WHEEL
pelican_next_meetup-0.1.1.dist-info/RECORD
pelican_next_meetup-0.1.1.dist-info/DESCRIPTION.rst
pelican_next_meetup-0.1.1.dist-info/metadata.json
