Metadata-Version: 2.0
Name: pelican-next-meetup
Version: 0.1.1
Summary: Pelican plugin to get info on your next meetup.
Home-page: https://github.com/SangSatori/pelican_next_meetup
Author: Arnis Jaundžeikars
Author-email: sangsatori@radiantmoons.me
License: MIT
Keywords: pelican plugins meetup
Platform: UNKNOWN
Classifier: Development Status :: 3 - Alpha
Classifier: Intended Audience :: Developers
Classifier: License :: OSI Approved :: MIT License
Classifier: Operating System :: OS Independent
Classifier: Programming Language :: Python :: 3
Classifier: Programming Language :: Python :: 3.2
Classifier: Programming Language :: Python :: 3.3
Classifier: Programming Language :: Python :: 3.4
Classifier: Topic :: Internet :: WWW/HTTP
Classifier: Topic :: Software Development :: Libraries :: Python Modules
Requires-Dist: requests
